komootgpx/__init__.py
komootgpx/__main__.py
komootgpx/__version__.py
komootgpx/api.py
komootgpx/gpxcompiler.py
komootgpx/komootgpx.py
komootgpx/utils.py
komootgpx-1.4.3.dist-info/licenses/LICENSE
komootgpx-1.4.3.dist-info/METADATA
komootgpx-1.4.3.dist-info/WHEEL
komootgpx-1.4.3.dist-info/entry_points.txt
komootgpx-1.4.3.dist-info/top_level.txt
komootgpx-1.4.3.dist-info/RECORD
