Metadata-Version: 2.4
Name: komootgpx
Version: 1.4.3
Summary: Download Komoot tracks and highlights as GPX files (including metadata). Supports bulk-download.
Author-email: Tim Schneeberger <tim.schneeberger@outlook.de>
License-Expression: GPL-3.0-only
Project-URL: Homepage, https://github.com/timschneeb/KomootGPX
Classifier: Development Status :: 5 - Production/Stable
Classifier: Intended Audience :: End Users/Desktop
Classifier: Programming Language :: Python :: 3
Classifier: Topic :: Internet
Classifier: Topic :: System :: Archiving
Requires-Python: >=3.6.0
License-File: LICENSE
Requires-Dist: argparse
Requires-Dist: certifi
Requires-Dist: chardet
Requires-Dist: gpxpy
Requires-Dist: colorama
Requires-Dist: idna
Requires-Dist: requests
Requires-Dist: urllib3
Dynamic: license-file
